{
    "Complete": "Terminer",
    "Continue": "Continuer",
    "Empty": "Vide",
    "Please sellect an option": "Veuillez sélectionner une option",
    "Where are your culinary roots from?": "D'où viennent vos racines culinaires ?",
    "Select the region that represents your cultural heritage.": "Sélectionnez la région qui représente votre héritage culturel.",
    "Africa": "Afrique",
    "North Africa": "Afrique du Nord",
    "Middle East": "Moyen-Orient",
    "Europe": "Europe",
    "Asia": "Asie",
    "Latin America": "Amérique latine",
    "Caribbean": "Caraïbes",
    "What's your favorite dish?": "Quel est votre plat préféré ?",
    "Pick the dish you enjoy the most.": "Choisissez le plat que vous préférez.",
    "Mafé": "Mafé",
    "Poulet yassa": "Poulet yassa",
    "Tajine": "Tajine",
    "Couscous": "Couscous",
    "Colombo de poulet": "Colombo de poulet",
    "Empanadas": "Empanadas",
    "Autre": "Autre",
    "What's your goal with our app?": "Quel est votre objectif avec notre application ?",
    "Choose the main reason you want to use Roots & Recipes.": "Choisissez la principale raison pour laquelle vous utilisez Roots & Recipes.",
    "Rediscover my culinary culture": "Redécouvrir ma culture culinaire",
    "Learn how to cook new dishes": "Apprendre à cuisiner de nouveaux plats",
    "Prepare menus for my family": "Préparer des menus pour ma famille",
    "Cook more easily on a daily basis": "Cuisiner plus facilement au quotidien",
    "Eat healthier without losing my roots": "Manger plus sainement sans perdre mes racines",
    "How often do you cook?": "À quelle fréquence cuisinez-vous ?",
    "Select your cooking frequency.": "Sélectionnez votre fréquence de cuisine.",
    "Every day": "Tous les jours",
    "A few times a week": "Quelques fois par semaine",
    "Occasionally": "Occasionnellement",
    "Please select an option": "Veuillez sélectionner une option",
    "Verify Email": "Vérifier l'email",
    "Enter ": "Entrez ",
    "Verification": "Vérification",
    " Code.": " Code.",
    "Enter the code that was sent to your email.": "Entrez le code envoyé à votre email.",
    "Didn't receive the code? ": "Vous n’avez pas reçu le code ? ",
    "Resend": "Renvoyer",
    "Verify": "Vérifier",
    "Forget Your ": "Mot de passe ",
    "Password": "oublié",
    "Enter your email address to reset your password.": "Entrez votre adresse email pour réinitialiser votre mot de passe.",
    "Email": "Email",
    "Enter your email": "Entrez votre email",
    "Please wait...": "Veuillez patienter...",
    "Get Verification Code": "Obtenir le code de vérification",
    "Now Reset Your ": "Réinitialisez votre ",
    "Password must have 6-8 characters.": "Le mot de passe doit contenir 6 à 8 caractères.",
    "New Password": "Nouveau mot de passe",
    "Enter your password": "Entrez votre mot de passe",
    "Confirm New Password": "Confirmez le nouveau mot de passe",
    "Reset Password": "Réinitialiser le mot de passe",
    "Welcome": "Bienvenue",
    "Now continue after register in ": "Continuez après votre inscription dans ",
    "“Mamafé”.": "“Mamafé”.",
    "Select an account": "Sélectionnez un compte",
    "Sign In to Your Account": "Connectez-vous à votre compte",
    "Remember me": "Se souvenir de moi",
    "Forgot Password": "Mot de passe oublié",
    "Don’t have an account?   ": "Vous n’avez pas de compte ?   ",
    "Create Account": "Créer un compte",
    "Full name": "Nom complet",
    "Enter your full name": "Entrez votre nom complet",
    "Confirm Password": "Confirmez le mot de passe",
    "Agree with ": "Accepter les ",
    "Terms and Conditions": "Termes et Conditions",
    "Sign Up": "S’inscrire",
    "Already have an account? ": "Vous avez déjà un compte ? ",
    "Sign In": "Se connecter",
    "Read more": "Lire plus",
    "Recent Blogs": "Blogs récents",
    "Search cultures, regions, cuisine types...": "Rechercher cultures, régions, types de cuisine...",
    "Explore by Region": "Explorer par région",
    "All Recipes": "Toutes les recettes",
    "Clear filter": "Réinitialiser le filtre",
    "Search your favorite recipes...": "Recherchez vos recettes préférées...",
    "All Difficulties": "Toutes difficultés",
    "Sort By": "Trier par",
    "No favorites yet": "Aucun favori pour le moment",
    "Start exploring our recipes and save your\nfavorites to build your personal collection": "Commencez à explorer nos recettes et enregistrez vos favoris\npour créer votre collection personnelle",
    "Start Exploring": "Commencer à explorer",
    "Trending This Week": "Tendances de la semaine",
    "Recommended For You": "Recommandé pour vous",
    "Popular From Your Heritage": "Populaire dans votre culture",
    "Hello, ": "Bonjour, ",
    "Let’s explore our recipes": "Découvrez nos recettes",
    "Search Recipe, cuisines...": "Recherchez une recette, une cuisine...",
    "Notifications": "Notifications",
    "There’s no notifications": "Aucune notification",
    "Your notifications will appear on\nthis page.": "Vos notifications apparaîtront sur\ncette page.",
    "minutes ago": "minutes ago",
    "hours ago": "heures ago",
    "days ago": "jours ago",
    "Food Music": "Musique culinaire",
    "Origin: ": "Origine : ",
    "Description": "Description",
    "Ingredients": "Ingrédients",
    "Instructions": "Instructions",
    "Cultural Background": "Contexte culturel",
    "Related Recipes": "Recettes associées",
    "Discover more delicious recipes from this region and learn about its rich culinary heritage.": "Découvrez d'autres recettes délicieuses de cette région et apprenez-en davantage sur son riche patrimoine culinaire.",
    "Explore ": "Explorer ",
    " Recipe": " Recette",
    "Explore Best and\nHealthy Food Recipe.": "Découvrez les meilleures recettes\nsaines et savoureuses.",
    "Dive into a world of culinary delights with our extensive collection of nutritious and delicious recipes": "Plongez dans un univers de délices culinaires grâce à notre large collection de recettes nutritives et délicieuses.",
    "Customize Your\nExperience.": "Personnalisez\nvotre expérience.",
    "Tailor your app experience by selecting your dietary preferences and favorite cuisines for personalized recipe recommendations.": "Personnalisez votre expérience en choisissant vos préférences alimentaires et cuisines favorites pour des recommandations adaptées.",
    "Get Started!": "Commencer !",
    "To personalize your experience, we just need a few details. Sign up and let’s get cooking!\n\n\n": "Pour personnaliser votre expérience, nous avons besoin de quelques détails. Inscrivez-vous et commençons à cuisiner !\n\n\n",
    "Explore Recipe": "Explorer les recettes",
    "Change Password": "Changer le mot de passe",
    "Current Password": "Mot de passe actuel",
    "Enter new password": "Entrez un nouveau mot de passe",
    "Re-enter new password": "Entrez de nouveau le mot de passe",
    "Edit Profile": "Modifier le profil",
    "Phone Number": "Numéro de téléphone",
    "Enter your phone number": "Entrez votre numéro de téléphone",
    "Save": "Enregistrer",
    "Edit your Preferences": "Modifier vos préférences",
    "My Recipes": "Mes recettes",
    "No recipes found.": "Aucune recette trouvée.",
    "Plan Management": "Gestion du plan",
    "Current Plan": "Plan actuel",
    "Premium User": "Utilisateur Premium",
    "Free User": "Utilisateur gratuit",
    "Next Billing Date": "Prochaine date de facturation",
    "Subscription Expired": "Abonnement expiré",
    "Plan": "Plan",
    "Amount": "Montant",
    "Renew Plan": "Renouveler le plan",
    "Change Plan": "Changer de plan",
    "Cancel Plan": "Annuler le plan",
    "N/A": "N/A",
    "Privacy Policy": "Politique de confidentialité",
    "No privacy policy found.": "Aucune politique de confidentialité trouvée.",
    "No user data": "Aucune donnée utilisateur",
    "Premium Plan": "Plan Premium",
    "You have access to all premium features": "Vous avez accès à toutes les fonctionnalités premium",
    "Next billing date": "Prochaine date de facturation",
    "Manage": "Gérer",
    "Account Settings": "Paramètres du compte",
    "Terms & Policies": "Termes et politiques",
    "Log Out": "Se déconnecter",
    "General Settings": "Paramètres généraux",
    "Delete Account": "Supprimer le compte",
    "Do you want to delete your account?": "Voulez-vous supprimer votre compte ?",
    "Cancel": "Annuler",
    "Delete": "Supprimer",
    "No Terms & Policies found.": "Aucun terme ou politique trouvé.",
    "Cover Image": "Image de couverture",
    "Upload your image": "Télécharger votre image",
    "Change the image": "Changer l’image",
    "Recipe Title*": "Titre de la recette*",
    "Prep Time (mins)*": "Temps de préparation (min)*",
    "Cook Time (mins)*": "Temps de cuisson (min)*",
    "Difficulty Level*": "Niveau de difficulté*",
    "Cultural Origin": "Origine culturelle",
    "Description*": "Description*",
    "Add": "Ajouter",
    "Name*": "Nom*",
    "Quantity*": "Quantité*",
    "Remove": "Supprimer",
    "Step {index}": "Étape {index}",
    "Cultural Background*": "Contexte culturel*",
    "Choose Your Plan": "Choisissez votre plan",
    "Select the plan that fits your culinary journey": "Sélectionnez le plan qui correspond à votre parcours culinaire",
    "Monthly": "Mensuel",
    "Yearly": "Annuel",
    "Save 17%": "Économisez 17%",
    "7-day free trial\nTry all premium features free for 7 days": "Essai gratuit de 7 jours\nDécouvrez toutes les fonctionnalités premium gratuitement",
    "Start Free": "Commencer gratuitement",
    "Subscribe Now": "S’abonner maintenant",
    "No commitment. Cancel anytime.": "Sans engagement. Annulez à tout moment.",
    "Home": "Accueil",
    "Explore": "Explorer",
    "Recipe": "Recette",
    "Favorites": "Favoris",
    "Blogs": "Blogs",
    "Profile": "Profil",
    "Easy": "Facile",
    "Medium": "Moyen",
    "Hard": "Difficile",
    "Popular": "Populaire",
    "Newest": "Le plus récent"
}